FP_Multiplier.sv
module FP_Multiplier 
(   input clk,
    input nreset,
    input wire [31:0] A,
    input wire [31:0] B,
    output logic [7:0] A_exponent, 
    output logic [7:0] B_exponent,
    output logic [23:0] A_mantissa, 
    output logic [23:0] B_mantissa,
    output logic [31:0] mul_result);
    
    logic [31:0] A_reg, B_reg;

    logic A_sign, B_sign;
    

    logic [31:0] mul_result_reg;

    logic result_sign;
    logic [7:0] result_exponent;
    logic [22:0] result_mantissa;
    
    logic [47:0] mantissa_mul;
    logic [7:0] exponent_diff;

    // Input of numbers used for the FP operation
    always_ff @(posedge clk, negedge nreset)
    begin
        if (nreset) 
        begin
            A_reg <= '0;
            B_reg <= '0;
            mul_result_reg <= '0;
        end
        else
        begin
            A_reg <= A;
            B_reg <= B;
            mul_result_reg <=  {result_sign, result_exponent, result_mantissa};
        end
    end

    assign A_sign = A_reg[31];
    assign B_sign = B_reg[31];
    assign A_exponent = A_reg[30:23];
    assign B_exponent = B_reg[30:23];
    assign A_mantissa = {1'b1, A_reg[22:0]};
    assign B_mantissa = {1'b1, B_reg[22:0]};
    
    // Combinational logic of the arithmetic operation
    always_comb
    begin

        // Sign of the result
        result_sign = (A_sign ^ B_sign); 

        // Exponent calculation
        exponent_diff = A_exponent + B_exponent - 8'd127;

        mantissa_mul = A_mantissa * B_mantissa;

        if (mantissa_mul[47]) begin
            // If the result is too large, we need to normalize it
            result_mantissa = mantissa_mul[46:24]; // Shift right by 1
            result_exponent = exponent_diff + 1; // Increase exponent
        end
        else begin
            // If the result is not too large, we can use it directly
            result_mantissa = mantissa_mul[45:23]; // Keep the 24 bits
            result_exponent = exponent_diff; // Use the exponent as is
        end


    end

    assign mul_result = mul_result_reg;

endmodule

FP_Multiplier_tb.sv
`timescale 1ns/1ps
module FP_Multiplier_tb ();

    // Input signals
    reg clk;
    reg nreset;
    reg [31:0] A;
    reg [31:0] B;

    // Output signal
    wire [31:0] mul_result;

    FP_Multiplier uut (
        .clk(clk),
        .nreset(nreset),
        .A(A),
        .B(B),
        .mul_result(mul_result)
    );

    // Dump signals for waveform analysis
    // This will create a VCD file for waveform analysis
    initial begin
        $dumpfile("wave.vcd");  // Output VCD file
        $dumpvars(0, FP_Multiplier_tb);       // Dump all signals in the testbench
    end

    // Clock generation for the with an 100 MHz     
    initial begin
        clk = 0;
        forever #5 clk = ~clk;

        if ($time > 2000) begin
            $display("Simulation time exceeded 2000 ns, stopping simulation.");
            $stop;
        end

    end

    task test_case;

        input [31:0] a;
        input [31:0] b;
        input [31:0] expected;

        begin
            A = a;
            B = b;

            $display("Test: %h * %h  = %h (Expected output: %h)", a, b, mul_result, expected);
            $display($time, " ns: A = %h, B = %h, Result = %h", A, B, mul_result);
            if (mul_result != expected) $display("Error: you are dolboeb!");
        end

    endtask

    initial begin

        nreset = 1;
        A = 0;
        B = 0;

        #10 nreset = 0;
        #15;

        $display ("Start the simulation with testing");

        // Test cases
        test_case(32'h3FC00000, 32'h3FC00000, 32'h40100000); // 1.5 * 1.5 = 2.25
        #10;
        test_case(32'h40000000, 32'h3FC00000, 32'h40400000); // 2.0 * 1.5 = 3.0
        #10;
        test_case(32'h40490FD0, 32'h402DF84D, 32'h4108A2B3); // 3.14159 * 2.71828 = 1.0
        #10;
        test_case(32'h3F9E0651, 32'h33D6BF95, 32'h33F142B1); // 1.2345678 * 0.0000001 = 1.0
        #10;
        test_case(32'h425C7E6B, 32'h4207F35C, 32'h44EA308B); // 55.123456 * 33.987654 = 1.0
        #10;
        test_case(32'h414B94E2, 32'h443EF4BC, 32'h4617DB1F); // 12.723848 * 763.824 = 9714
        #40;

        $display ("Simulation is finished");
        $stop;


    end



endmodule

FP_arithmetic.sim/sim_1/behav/xsim/wave.vcd
$date
   Wed Jun 18 18:51:10 2025
$end

$version
  2023.2
  $dumpfile ("wave.vcd") 
$end

$timescale
  1ps
$end

$scope module FP_Multiplier_tb $end
$var reg 1 ! clk $end
$var reg 1 " nreset $end
$var reg 32 # A [31:0] $end
$var reg 32 $ B [31:0] $end
$var wire 32 % mul_result [31:0] $end
$scope module uut $end
$var wire 1 & clk $end
$var wire 1 ' nreset $end
$var wire 32 ( A [31:0] $end
$var wire 32 ) B [31:0] $end
$var wire 32 % mul_result [31:0] $end
$var reg 32 * A_reg [31:0] $end
$var reg 32 + B_reg [31:0] $end
$var reg 1 , A_sign $end
$var reg 1 - B_sign $end
$var reg 8 . A_exponent [7:0] $end
$var reg 8 / B_exponent [7:0] $end
$var reg 24 0 A_mantissa [23:0] $end
$var reg 24 1 B_mantissa [23:0] $end
$var reg 32 2 mul_result_reg [31:0] $end
$var reg 1 3 result_sign $end
$var reg 8 4 result_exponent [7:0] $end
$var reg 23 5 result_mantissa [22:0] $end
$var reg 48 6 mantissa_mul [47:0] $end
$var reg 8 7 exponent_diff [7:0] $end
$upscope $end
$scope task test_case $end
$var reg 32 8 a [31:0] $end
$var reg 32 9 b [31:0] $end
$var reg 32 : expected [31:0] $end
$upscope $end
$upscope $end
$enddefinitions $end

#0
$dumpvars
0!
1"
b0 #
b0 $
bx %
0&
1'
b0 (
b0 )
bx *
bx +
x,
x-
bx .
bx /
b1xxxxxxxxxxxxxxxxxxxxxxx 0
b1xxxxxxxxxxxxxxxxxxxxxxx 1
bx 2
x3
bx 4
bx 5
bx 6
bx 7
bx 8
bx 9
bx :
$end

#5000
1!
b0 %
1&
b0 *
b0 +
0,
0-
b0 .
b0 /
b100000000000000000000000 0
b100000000000000000000000 1
b0 2
03
b10000001 4
b0 5
b10000000000000000000000000000000000000000000000 6
b10000001 7

#10000
0!
0"
b1000000100000000000000000000000 %
0&
0'
b1000000100000000000000000000000 2

#15000
1!
1&

#20000
0!
0&

#25000
1!
b111111110000000000000000000000 #
b111111110000000000000000000000 $
1&
b111111110000000000000000000000 (
b111111110000000000000000000000 )
b111111110000000000000000000000 *
b111111110000000000000000000000 +
b1111111 .
b1111111 /
b110000000000000000000000 0
b110000000000000000000000 1
b10000000 4
b100000000000000000000 5
b100100000000000000000000000000000000000000000000 6
b1111111 7
b111111110000000000000000000000 8
b111111110000000000000000000000 9
b1000000000100000000000000000000 :

#30000
0!
0&

#35000
1!
b1000000000000000000000000000000 #
b1000000000100000000000000000000 %
1&
b1000000000000000000000000000000 (
b1000000000000000000000000000000 *
b10000000 .
b100000000000000000000000 0
b1000000000100000000000000000000 2
b10000000000000000000000 5
b11000000000000000000000000000000000000000000000 6
b10000000 7
b1000000000000000000000000000000 8
b1000000010000000000000000000000 :

#40000
0!
0&

#45000
1!
b1000000010010010000111111010000 #
b1000000001011011111100001001101 $
b1000000010000000000000000000000 %
1&
b1000000010010010000111111010000 (
b1000000001011011111100001001101 )
b1000000010010010000111111010000 *
b1000000001011011111100001001101 +
b10000000 /
b110010010000111111010000 0
b101011011111100001001101 1
b1000000010000000000000000000000 2
b10000010 4
b10001010001010110011 5
b100010001010001010110011010110110100000110010000 6
b10000001 7
b1000000010010010000111111010000 8
b1000000001011011111100001001101 9
b1000001000010001010001010110011 :

#50000
0!
0&

#55000
1!
b111111100111100000011001010001 #
b110011110101101011111110010101 $
b1000001000010001010001010110011 %
1&
b111111100111100000011001010001 (
b110011110101101011111110010101 )
b111111100111100000011001010001 *
b110011110101101011111110010101 +
b1111111 .
b1100111 /
b100111100000011001010001 0
b110101101011111110010101 1
b1000001000010001010001010110011 2
b1101000 4
b1001000111110001010 5
b100001001000111110001010011001100001110000100101 6
b1100111 7
b111111100111100000011001010001 8
b110011110101101011111110010101 9
b110011111100010100001010110001 :

#60000
0!
0&

#65000
1!
b1000010010111000111111001101011 #
b1000010000001111111001101011100 $
b110100000001001000111110001010 %
1&
b1000010010111000111111001101011 (
b1000010000001111111001101011100 )
b1000010010111000111111001101011 *
b1000010000001111111001101011100 +
b10000100 .
b10000100 /
b110111000111111001101011 0
b100001111111001101011100 1
b110100000001001000111110001010 2
b10001001 4
b11010100011000010001011 5
b11101010001100001000101101010011111111101110100 6
b10001001 7
b1000010010111000111111001101011 8
b1000010000001111111001101011100 9
b1000100111010100011000010001011 :

#70000
0!
0&

#75000
1!
b1000001010010111001010011100010 #
b1000100001111101111010010111100 $
b1000100111010100011000010001011 %
1&
b1000001010010111001010011100010 (
b1000100001111101111010010111100 )
b1000001010010111001010011100010 *
b1000100001111101111010010111100 +
b10000010 .
b10001000 /
b110010111001010011100010 0
b101111101111010010111100 1
b1000100111010100011000010001011 2
b10001100 4
b101111101101100011111 5
b100101111101101100011111001001001011110111111000 6
b10001011 7
b1000001010010111001010011100010 8
b1000100001111101111010010111100 9
b1000110000101111101101100011111 :

#80000
0!
0&

#85000
1!
b1000110000101111101101100011111 %
1&
b1000110000101111101101100011111 2

